Rtool_py/__init__.py
Rtool_py/print_info.py
Rtool_Neil-0.0.10.dist-info/LICENSE
Rtool_Neil-0.0.10.dist-info/METADATA
Rtool_Neil-0.0.10.dist-info/WHEEL
Rtool_Neil-0.0.10.dist-info/top_level.txt
Rtool_Neil-0.0.10.dist-info/RECORD
