Metadata-Version: 2.1
Name: Rtool-Neil
Version: 0.0.10
Summary: A small example package
Home-page: 
Author: Jianhong Gao
Author-email: 772962760@qq.com
License: UNKNOWN
Platform: UNKNOWN
Classifier: Programming Language :: Python :: 3
Classifier: License :: OSI Approved :: MIT License
Classifier: Operating System :: OS Independent
License-File: LICENSE
